README.md
licence.txt
setup.cfg
setup.py
JFQ/__init__.py
JFQ.egg-info/PKG-INFO
JFQ.egg-info/SOURCES.txt
JFQ.egg-info/dependency_links.txt
JFQ.egg-info/requires.txt
JFQ.egg-info/top_level.txt
JFQ/BBG/__init__.py
JFQ/BBG/core.py
JFQ/HELPERS/__init__.py
JFQ/HELPERS/databases.py
JFQ/HELPERS/general.py
JFQ/HELPERS/misc.py
JFQ/HELPERS/pandas_ext.py
JFQ/HELPERS/plotly_ext.py
JFQ/HELPERS/stats.py
JFQ/TREE/__init__.py
JFQ/TREE/core.py