Metadata-Version: 2.1
Name: JFQ
Version: 0.1.14
Summary: various utilities
Home-page: 
Author: 
Author-email: 
License: GNU2L
Keywords: openAPI
Classifier: Development Status :: 3 - Alpha
Classifier: Intended Audience :: Developers
Classifier: Topic :: Software Development :: Documentation
Classifier: License :: OSI Approved :: GNU General Public License v3 (GPLv3)
Classifier: Programming Language :: Python :: 3.9
Classifier: Programming Language :: Python :: 3.10
Classifier: Programming Language :: Python :: 3.11
License-File: licence.txt
